dpl_geodb/__init__.py
dpl_geodb/db_settings.txt
dpl_geodb/geo_ops.py
dpl_geodb/picture_reference.py
dpl_geodb/queries.py
geotagging_alexr96-0.0.29.dist-info/LICENCE
geotagging_alexr96-0.0.29.dist-info/METADATA
geotagging_alexr96-0.0.29.dist-info/WHEEL
geotagging_alexr96-0.0.29.dist-info/top_level.txt
geotagging_alexr96-0.0.29.dist-info/RECORD
