Metadata-Version: 2.1
Name: geotagging-alexr96
Version: 0.0.29
Summary: Geotagging database package
Home-page: https://github.com/alex-96-devpipeline/geotagging_db
Author: Alex Roy
Author-email: Alex@devpipeline.com
License: UNKNOWN
Platform: UNKNOWN
Classifier: Programming Language :: Python :: 3
Classifier: License :: OSI Approved :: The Unlicense (Unlicense)
Classifier: Operating System :: OS Independent
Requires-Python: >=3.6
Requires-Dist: psycopg2-binary
